OLD/OLDLog.py
OLD/__init__.py
OLD/CLI/CLIDraw.py
OLD/CLI/CLIElem.py
OLD/CLI/CLILog.py
OLD/CLI/CLIMain.py
OLD/CLI/CLIRes.py
OLD/CLI/CLIResLoad.py
OLD/CLI/CONSTS.py
OLD/CLI/__init__.py
OLD/TEL/CONSTS.py
OLD/TEL/TELFront.py
OLD/TEL/TELLog.py
OLD/TEL/TELMain.py
OLD/TEL/TELShell.py
OLD/TEL/__init__.py
Old_Linkage_Dev-0.0.4.dist-info/LICENSE
Old_Linkage_Dev-0.0.4.dist-info/METADATA
Old_Linkage_Dev-0.0.4.dist-info/WHEEL
Old_Linkage_Dev-0.0.4.dist-info/top_level.txt
Old_Linkage_Dev-0.0.4.dist-info/RECORD
