Metadata-Version: 2.1
Name: Old-Linkage-Dev
Version: 0.0.4
Summary: a module to develop and apply old-style links
Home-page: https://github.com/Tarcadia/Old-Linkage-Dev
Author: Tarcadia
Author-email: tarcadia@qq.com
License: UNKNOWN
Project-URL: Bug Tracker, https://github.com/Tarcadia/Old-Linkage-Dev/issues
Keywords: telnet,CLI,website
Platform: UNKNOWN
Classifier: Development Status :: 2 - Pre-Alpha
Classifier: Programming Language :: Python :: 3
Classifier: License :: OSI Approved :: GNU General Public License v3 (GPLv3)
Classifier: Operating System :: OS Independent
Requires-Python: >=3.7
License-File: LICENSE
